belial_db/__about__.py
belial_db/__init__.py
belial_db/data/__init__.py
belial_db/data/vector_3.py
belial_db/data/vector_4.py
belial_db/models/__init__.py
belial_db/models/asset.py
belial_db/models/asset_file.py
belial_db/models/map.py
belial_db/models/relationships.py
belial_db/models/vector_3_type.py
belial_db/models/vector_4_type.py
belial_db/repos/__init__.py
belial_db/repos/asset_file_repo.py
belial_db/repos/asset_repo.py
belial_db/repos/map_repo.py
manmade2_belialdb-1.0.17.dist-info/METADATA
manmade2_belialdb-1.0.17.dist-info/WHEEL
manmade2_belialdb-1.0.17.dist-info/licenses/LICENSE.txt
manmade2_belialdb-1.0.17.dist-info/RECORD
